athena/__init__.py
athena/agents/__init__.py
athena/agents/client.py
athena/agents/drive/__init__.py
athena/agents/drive/client.py
athena/agents/drive/raw_client.py
athena/agents/general/__init__.py
athena/agents/general/client.py
athena/agents/general/raw_client.py
athena/agents/raw_client.py
athena/agents/research/__init__.py
athena/agents/research/client.py
athena/agents/research/raw_client.py
athena/agents/sql/__init__.py
athena/agents/sql/client.py
athena/agents/sql/raw_client.py
athena/aop/__init__.py
athena/aop/client.py
athena/aop/raw_client.py
athena/assets/__init__.py
athena/assets/client.py
athena/assets/raw_client.py
athena/base_client.py
athena/client.py
athena/core/__init__.py
athena/core/api_error.py
athena/core/client_wrapper.py
athena/core/datetime_utils.py
athena/core/file.py
athena/core/force_multipart.py
athena/core/http_client.py
athena/core/http_response.py
athena/core/jsonable_encoder.py
athena/core/pydantic_utilities.py
athena/core/query_encoder.py
athena/core/remove_none_from_dict.py
athena/core/request_options.py
athena/core/serialization.py
athena/databases/__init__.py
athena/databases/client.py
athena/databases/raw_client.py
athena/databases/types/__init__.py
athena/databases/types/data.py
athena/environment.py
athena/errors/__init__.py
athena/errors/bad_request_error.py
athena/errors/conflict_error.py
athena/errors/content_too_large_error.py
athena/errors/forbidden_error.py
athena/errors/internal_server_error.py
athena/errors/not_found_error.py
athena/errors/not_implemented_error.py
athena/errors/service_unavailable_error.py
athena/errors/unauthorized_error.py
athena/errors/unprocessable_entity_error.py
athena/errors/unsupported_media_type_error.py
athena/py.typed
athena/query/__init__.py
athena/query/client.py
athena/query/raw_client.py
athena/query/types/__init__.py
athena/query/types/query_execute_request_database_asset_ids.py
athena/threads/__init__.py
athena/threads/client.py
athena/threads/raw_client.py
athena/tools/__init__.py
athena_intelligence-0.1.515.dist-info/METADATA
athena_intelligence-0.1.515.dist-info/WHEEL
athena_intelligence-0.1.515.dist-info/RECORD
