Metadata-Version: 2.1
Name: athena-intelligence
Version: 0.1.515
Summary: Athena Intelligence Python Library
Requires-Python: >=3.9,<4.0
Classifier: Intended Audience :: Developers
Classifier: Operating System :: MacOS
Classifier: Operating System :: Microsoft :: Windows
Classifier: Operating System :: OS Independent
Classifier: Operating System :: POSIX
Classifier: Operating System :: POSIX :: Linux
Classifier: Programming Language :: Python
Classifier: Programming Language :: Python :: 3
Classifier: Programming Language :: Python :: 3.9
Classifier: Programming Language :: Python :: 3.10
Classifier: Programming Language :: Python :: 3.11
Classifier: Programming Language :: Python :: 3.12
Classifier: Programming Language :: Python :: 3.8
Classifier: Topic :: Software Development :: Libraries :: Python Modules
Classifier: Typing :: Typed
Requires-Dist: fastapi (==0.115.10)
Requires-Dist: httpx (>=0.21.2)
Requires-Dist: langchain_core (>=0.3.40,<0.4.0)
Requires-Dist: langserve (>=0.3.1,<0.4.0)
Requires-Dist: pydantic (>=1.9.2)
Requires-Dist: pydantic-core (>=2.18.2)
Requires-Dist: python-magic (==0.4.27)
Requires-Dist: typing_extensions (>=4.0.0)
